flask_authnz_ldap_rbac/__init__.py
flask_authnz_ldap_rbac/flask_authnz_ldap_rbac.py
flask_authnz_ldap_rbac-0.2.2.dist-info/DESCRIPTION.rst
flask_authnz_ldap_rbac-0.2.2.dist-info/METADATA
flask_authnz_ldap_rbac-0.2.2.dist-info/RECORD
flask_authnz_ldap_rbac-0.2.2.dist-info/WHEEL
flask_authnz_ldap_rbac-0.2.2.dist-info/metadata.json
flask_authnz_ldap_rbac-0.2.2.dist-info/top_level.txt
flask_authnz_ldap_rbac-0.2.2.dist-info/version.txt
flask_authnz_ldap_rbac-0.2.2.dist-info/version_full.txt
