Metadata-Version: 2.0
Name: flask-authnz-ldap-rbac
Version: 0.2.2
Summary: Uses AuthN/AuthZ environment variables from Apache mod_authnz_ldap to enforce access controls on Flask apps
Home-page: https://github.com/brandond/flask-authnz-ldap-rbac
Author: Brandon Davidson
Author-email: brad@oatmail.org
License: UNKNOWN
Platform: UNKNOWN
Classifier: Development Status :: 4 - Beta
Classifier: Framework :: Flask
Classifier: License :: OSI Approved :: Apache Software License
Classifier: Programming Language :: Python :: 2.7
Classifier: Programming Language :: Python :: 3.5
Classifier: Programming Language :: Python :: 3.6
Classifier: Programming Language :: Python :: 3.7
Classifier: Topic :: System :: Systems Administration :: Authentication/Directory :: LDAP
Requires-Python: >=2.7
Requires-Dist: flask
Provides-Extra: dev
Requires-Dist: setuptools-version-command; extra == 'dev'
